gmx_clusterbyfeatures-0.1.29.dist-info/RECORD
gmx_clusterbyfeatures-0.1.29.dist-info/WHEEL
gmx_clusterbyfeatures-0.1.29.dist-info/entry_points.txt
gmx_clusterbyfeatures-0.1.29.dist-info/top_level.txt
gmx_clusterbyfeatures-0.1.29.dist-info/METADATA
gmx_clusterbyfeatures-0.1.29.dist-info/licenses/LICENSE
gmx_clusterByFeatures/holeclustersplot.py
gmx_clusterByFeatures/holefeatures.py
gmx_clusterByFeatures/_version.py
gmx_clusterByFeatures/matplot.py
gmx_clusterByFeatures/__init__.py
gmx_clusterByFeatures/holeOutputProcessor.py
gmx_clusterByFeatures/featuresplotcmd.py
gmx_clusterByFeatures/holeplot.py
gmx_clusterByFeatures/gmx_clusterByFeatures.cpython-311-darwin.so
gmx_clusterByFeatures/main.py
gmx_clusterByFeatures/featuresplotter.py
gmx_clusterByFeatures/top/export.dlg
gmx_clusterByFeatures/top/ffoplsaa.itp
gmx_clusterByFeatures/top/spc.itp
gmx_clusterByFeatures/top/ffG53a6.itp
gmx_clusterByFeatures/top/flexspce.itp
gmx_clusterByFeatures/top/atom_nom.tbl
gmx_clusterByFeatures/top/table6-12.xvg
gmx_clusterByFeatures/top/table6-10.xvg
gmx_clusterByFeatures/top/surface.dat
gmx_clusterByFeatures/top/tip3p.itp
gmx_clusterByFeatures/top/ffG53a5.itp
gmx_clusterByFeatures/top/table6-9.xvg
gmx_clusterByFeatures/top/phbres.dat
gmx_clusterByFeatures/top/table6-8.xvg
gmx_clusterByFeatures/top/flexspc.itp
gmx_clusterByFeatures/top/table6-11.xvg
gmx_clusterByFeatures/top/ca-shift.dat
gmx_clusterByFeatures/top/tip4p.gro
gmx_clusterByFeatures/top/tip4p.itp
gmx_clusterByFeatures/top/tip5p.gro
gmx_clusterByFeatures/top/residues.dtd
gmx_clusterByFeatures/top/xlateat.dat
gmx_clusterByFeatures/top/README
gmx_clusterByFeatures/top/ffG43a2.itp
gmx_clusterByFeatures/top/ha-shift.dat
gmx_clusterByFeatures/top/cb-shift.dat
gmx_clusterByFeatures/top/spce.itp
gmx_clusterByFeatures/top/ffG43a1.itp
gmx_clusterByFeatures/top/defselection.dat
gmx_clusterByFeatures/top/co-shift.dat
gmx_clusterByFeatures/top/refi_aa.dat
gmx_clusterByFeatures/top/residues.xml
gmx_clusterByFeatures/top/bonds.dlg
gmx_clusterByFeatures/top/ps.m2p
gmx_clusterByFeatures/top/ffG45a3.itp
gmx_clusterByFeatures/top/ions.itp
gmx_clusterByFeatures/top/spc216.gro
gmx_clusterByFeatures/top/specbond.dat
gmx_clusterByFeatures/top/edissoc.dat
gmx_clusterByFeatures/top/random.dat
