Metadata-Version: 2.4
Name: gmx_clusterByFeatures
Version: 0.1.29
Summary: Features Based Conformational Clustering of Molecular Dynamics trajectories.
Author-email: Rajendra Kumar <rjdkmr@gmail.com>
License: GNU General Public License v3 (GPLv3)
Project-URL: homepage, https://gmx-clusterbyfeatures.readthedocs.io/
Project-URL: repository, https://github.com/rjdkmr/gmx_clusterByFeatures
Keywords: Molecular Modeling,Molecular Dynamics Simulations,Computational Chemistry,Computational Biophysics,Clustering
Classifier: Environment :: Console
Classifier: Intended Audience :: Developers
Classifier: Intended Audience :: End Users/Desktop
Classifier: Intended Audience :: Science/Research
Classifier: License :: OSI Approved :: GNU General Public License v3 (GPLv3)
Classifier: Natural Language :: English
Classifier: Operating System :: MacOS
Classifier: Operating System :: POSIX :: Linux
Classifier: Topic :: Scientific/Engineering :: Bio-Informatics
License-File: LICENSE
Requires-Dist: numpy>=1.6
Requires-Dist: scipy>=0.9
Requires-Dist: matplotlib>=1.1.0
Requires-Dist: scikit-learn>=0.19.0
Dynamic: license-file
